__init__.py
barter_fastapi_auth/__init__.py
barter_fastapi_auth/auth.py
barter_fastapi_auth/base.py
barter_fastapi_auth/models.py
barter_fastapi_auth/permissions.py
barter_fastapi_auth/providers.py
barter_fastapi_auth/services.py
barter_fastapi_auth/settings.py
barter_fastapi_auth/test_factory.py
barter_fastapi_auth-0.1.1.dist-info/LICENSE
barter_fastapi_auth-0.1.1.dist-info/METADATA
barter_fastapi_auth-0.1.1.dist-info/WHEEL
barter_fastapi_auth-0.1.1.dist-info/top_level.txt
barter_fastapi_auth-0.1.1.dist-info/RECORD
