Metadata-Version: 2.1
Name: barter-fastapi-auth
Version: 0.1.1
Summary: Barter authentication package for FastApi
Home-page: https://github.com/kabilovtoha/barter_fastapi_auth
Author: akatoha
Author-email: kabilov <kabilov2011@gmail.com>
License: BSD
Project-URL: Homepage, https://github.com/kabilovtoha/barter_fastapi_auth
Project-URL: Bug Tracker, https://github.com/kabilovtoha/barter_fastapi_auth/issues
Classifier: Programming Language :: Python :: 3
Classifier: License :: OSI Approved :: MIT License
Classifier: Operating System :: OS Independent
Requires-Python: >=3.10
License-File: LICENSE
Requires-Dist: redis >=4.6.0
Requires-Dist: fastapi ==0.98.0
Requires-Dist: pydantic ==1.10.9
Requires-Dist: httpx >=0.24.1
Requires-Dist: factory-boy >=3.2.1
Requires-Dist: faker >=18.11.1
